s3tool/__init__.py
s3tool/download.py
s3tool/main.py
s3tool/upload.py
taichu-s3tool/__init__.py
taichu-s3tool/download.py
taichu-s3tool/main.py
taichu-s3tool/upload.py
taichu_s3tool-1.0.0.dist-info/METADATA
taichu_s3tool-1.0.0.dist-info/WHEEL
taichu_s3tool-1.0.0.dist-info/top_level.txt
taichu_s3tool-1.0.0.dist-info/RECORD
